indexer/__init__.py
indexer/client_auth.py
indexer/config.py
indexer/defaults.py
indexer/delocate.py
indexer/generate.py
indexer/index.py
indexer/metadata_manager.py
indexer/py.typed
indexer/metadata/__init__.py
indexer/metadata/basic.py
indexer/metadata/i3.py
indexer/metadata/real/__init__.py
indexer/metadata/real/data_exp.py
indexer/metadata/real/filename_patterns.py
indexer/metadata/real/l2.py
indexer/metadata/real/pfdst.py
indexer/metadata/real/pffilt.py
indexer/metadata/real/pfraw.py
indexer/metadata/simulation/__init__.py
indexer/metadata/simulation/data_sim.py
indexer/metadata/simulation/filename_patterns.py
indexer/metadata/simulation/iceprod_tools.py
indexer/utils/__init__.py
indexer/utils/file_utils.py
indexer/utils/utils.py
resources/filename_patterns/__init__.py
resources/filename_patterns/by_frequency.py
resources/filename_patterns/example_finder.py
resources/filename_patterns/filename_pattern_finder.py
resources/filename_patterns/filename_pattern_regexer.py
resources/filename_patterns/fpf_stage2.1.py
resources/find_nonindexed/__init__.py
resources/find_nonindexed/get_nonindexed_files.py
resources/find_nonindexed/make_condor.py
resources/path_collector/__init__.py
resources/path_collector/common_args.py
resources/path_collector/find_unfinished.py
resources/path_collector/path_collector.py
resources/path_collector/path_collector_make_condor.py
resources/path_collector/traverser.py
tests/integration/__init__.py
tests/integration/real/__init__.py
tests/integration/real/exp_data.py
tests/integration/real/test_data_exp_metadata.py
tests/integration/resources/__init__.py
tests/integration/resources/test_path_collector.py
tests/integration/simulation/__init__.py
tests/integration/simulation/sim_data.py
tests/integration/simulation/test_data_sim_metadata.py
tests/unit/__init__.py
tests/unit/indexer/__init__.py
tests/unit/indexer/test_metadata_manager.py
tests/unit/indexer/test_path_filtering.py
tests/unit/real/__init__.py
wipac_file_catalog_indexer-2.0.2.dist-info/LICENSE
wipac_file_catalog_indexer-2.0.2.dist-info/METADATA
wipac_file_catalog_indexer-2.0.2.dist-info/WHEEL
wipac_file_catalog_indexer-2.0.2.dist-info/top_level.txt
wipac_file_catalog_indexer-2.0.2.dist-info/RECORD
