Metadata-Version: 2.1
Name: wipac-file-catalog-indexer
Version: 2.0.2
Summary: Indexing package and scripts for the File Catalog
Home-page: https://github.com/WIPACrepo/file-catalog-indexer
Download-URL: https://pypi.org/project/wipac-file-catalog-indexer/
Author: WIPAC Developers
Author-email: developers@icecube.wisc.edu
License: MIT
Project-URL: Tracker, https://github.com/WIPACrepo/file-catalog-indexer/issues
Project-URL: Source, https://github.com/WIPACrepo/file-catalog-indexer
Keywords: indexer,metadata,data,warehouse,archive,L2,PFDST,PFFilt,PFRaw,i3,simulation,File,Catalog,iceprod,WIPAC,IceCube
Classifier: Development Status :: 5 - Production/Stable
Classifier: License :: OSI Approved :: MIT License
Classifier: Programming Language :: Python :: 3.8
Classifier: Programming Language :: Python :: 3.9
Classifier: Programming Language :: Python :: 3.10
Classifier: Programming Language :: Python :: 3.11
Requires-Python: <3.12,>=3.8
License-File: LICENSE
Requires-Dist: PyMySQL
Requires-Dist: bitmath
Requires-Dist: iceprod
Requires-Dist: more-itertools
Requires-Dist: requests
Requires-Dist: requests-futures
Requires-Dist: requests-toolbelt
Requires-Dist: typing-extensions
Requires-Dist: wipac-file-catalog
Requires-Dist: wipac-rest-tools
Requires-Dist: xmltodict
Provides-Extra: dev
Requires-Dist: coloredlogs ; extra == 'dev'
Requires-Dist: flake8 ; extra == 'dev'
Requires-Dist: mypy ; extra == 'dev'
Requires-Dist: natsort ; extra == 'dev'
Requires-Dist: pycycle ; extra == 'dev'
Requires-Dist: pytest ; extra == 'dev'
Requires-Dist: pytest-asyncio ; extra == 'dev'
Requires-Dist: pytest-cov ; extra == 'dev'
Requires-Dist: pytest-mock ; extra == 'dev'
Requires-Dist: requests ; extra == 'dev'
Requires-Dist: requests-mock ; extra == 'dev'
Requires-Dist: ruff ; extra == 'dev'
Requires-Dist: types-PyMySQL ; extra == 'dev'
Requires-Dist: types-PyYAML ; extra == 'dev'
Requires-Dist: types-requests ; extra == 'dev'
